cossign/__init__.py
cossign/config.py
cossign/cossign.py
cossign-0.0.3.dist-info/METADATA
cossign-0.0.3.dist-info/RECORD
cossign-0.0.3.dist-info/WHEEL
cossign-0.0.3.dist-info/entry_points.txt
cossign-0.0.3.dist-info/top_level.txt
