Metadata-Version: 2.1
Name: cossign
Version: 0.0.3
Summary: provide temporary credential for accessing cos resource
Home-page: https://cloud.tencent.com/document/product/436
Author: rickenwang
Author-email: rickenwang@tencent.com
License: UNKNOWN
Platform: UNKNOWN
Classifier: Programming Language :: Python :: 3
Classifier: License :: OSI Approved :: MIT License
Classifier: Operating System :: OS Independent
Requires-Dist: flask (>=1.0.2)
